binning/__init__.py
binning/binprocessing.py
binning/calprocessing.py
binning/chimerge_bin.py
binning/constants.py
binning/custom_bin.py
binning/distance_bin.py
binning/enumerate_bin.py
binning/enums.py
binning/frequency_bin.py
binning/log_utils.py
binning/tool.py
binning/version.py
binning/woe_iv_cal.py
binning/wrap_utils.py
binning-0.1.1.dist-info/LICENSE
binning-0.1.1.dist-info/METADATA
binning-0.1.1.dist-info/WHEEL
binning-0.1.1.dist-info/top_level.txt
binning-0.1.1.dist-info/RECORD
