Metadata-Version: 2.1
Name: binning
Version: 0.1.1
Summary: feature bin
Home-page: https://github.com/xkandj/binning
Author: xkandj
Author-email: lliu606@hotmail.com
License: UNKNOWN
Keywords: feature bin
Platform: UNKNOWN
Classifier: Development Status :: 5 - Production/Stable
Classifier: Intended Audience :: Developers
Classifier: License :: OSI Approved :: Apache Software License
Classifier: Topic :: Software Development :: Libraries :: Python Modules
Classifier: Programming Language :: Python :: 3
Classifier: Programming Language :: Python :: 3 :: Only
Classifier: Programming Language :: Python :: 3.6
Classifier: Programming Language :: Python :: 3.7
Classifier: Programming Language :: Python :: 3.8
Classifier: Programming Language :: Python :: 3.9
Classifier: Programming Language :: Python :: 3.10
Requires-Python: >=3.7
Requires-Dist: pandas (>=1.3)
Requires-Dist: numpy (>=1.18)
Requires-Dist: joblib (>=0.13)
Requires-Dist: concurrent-log (>=1.0)
